scrappify/__init__.py
scrappify/cli.py
scrappify/exceptions.py
scrappify/patterns.py
scrappify/core/__init__.py
scrappify/core/downloader.py
scrappify/core/scraper.py
scrappify/core/utils.py
scrappify-0.0.1.dist-info/METADATA
scrappify-0.0.1.dist-info/WHEEL
scrappify-0.0.1.dist-info/entry_points.txt
scrappify-0.0.1.dist-info/top_level.txt
scrappify-0.0.1.dist-info/RECORD
