Metadata-Version: 2.4
Name: scrappify
Version: 0.0.1
Summary: A powerful web scraping and downloading utility
Home-page: https://github.com/ByteBreach/scrappify
Author: hackinglab
Author-email: mrfidal@proton.me
Project-URL: Bug Tracker, https://github.com/ByteBreach/scrappify/issues
Project-URL: Documentation, https://github.com/ByteBreach/scrappify#readme
Project-URL: Source Code, https://github.com/ByteBreach/scrappify
Keywords: scraping,web scraping,website downloader,crawler,web crawler,data extraction,regex,hackinglab,mrfidal,email extractor,file downloader,python scraping,automation
Classifier: Programming Language :: Python :: 3
Classifier: License :: OSI Approved :: MIT License
Classifier: Operating System :: OS Independent
Classifier: Topic :: Internet :: WWW/HTTP
Classifier: Topic :: Internet :: WWW/HTTP :: Indexing/Search
Classifier: Topic :: Utilities
Classifier: Development Status :: 5 - Production/Stable
Requires-Python: >=3.6
Requires-Dist: requests
Requires-Dist: beautifulsoup4
Dynamic: author
Dynamic: author-email
Dynamic: classifier
Dynamic: description
Dynamic: description-content-type
Dynamic: home-page
Dynamic: keywords
Dynamic: project-url
Dynamic: requires-dist
Dynamic: requires-python
Dynamic: summary
